{"id": 38
,"title":{"text":"第三十八回　林瀟湘魁奪菊花詩　薛蘅蕪諷和螃蟹詠"}
,"video":"https://youtu.be/2QVeE8B-G8Q"
,"content":[
	{"prescript":""
	,"text":"\t\t【回前批語】\n\n"
	,"critique":[{"【回前批語】":[{"critic":"蒙回前總批","comment":"美人用別號，亦新奇花樣，且韻且雅，呼去覺滿口生香。起社出自探春意，作者已伏下興利除弊之文也。此回從放筆寫詩寫詞作札，看他詩復詩，詞複詞，札復札，總不相犯。"}
				,{"critic":"蒙回前總批","comment":"湘雲，詩客也，前回寫之其今才起社，後用不即不離閑人數語數折，仍歸社中。何巧活之筆如此？"}
				,{"critic":"庚辰","comment":"題曰「菊花詩」、「螃蟹詠」，偽自太君前阿鳳若許詼諧中不失體、鴛鴦平兒寵婢中多少放肆之迎合取樂寫來，似難入題，卻輕輕用弄水戲魚之看花等遊頑事及王夫人云「這裡風大」一句收住入題，並無纖毫牽強，此重作輕抹法也。妙極！好看煞！"}]}]
	}
	,{"prescript":""
    ,"text":" \t\t\n\n\n\n\n\n"
	}
	,{"id": "1"
	,"text":"\t\t話說寶釵、湘雲二人計議已妥，一宿無話。"
	}
	,{"id": "2"
	,"text":"湘雲次日便請賈母等賞桂花。賈母等都說道：「是他有興頭，須要擾他這雅興。」"
	,"critique":[{"」":[{"critic":"庚辰雙行夾批","comment":"若在世俗小家，則云：「你是客，在我們舍下，怎麼反擾你的呢？」一何可笑。"}]}]
	}
	,{"id":"3"
	,"text":"至午，果然賈母帶了王夫人、鳳姐兼請薛姨媽等進園來。賈母因問：「那一處好？」"
	,"critique":[{"那一處好":[{"critic":"庚辰雙行夾批","comment":"必如此問方好。"}]}]
	}
	,{"id":"4"
	,"text":"王夫人道：「憑老太太愛在那一處，就在那一處。」"
	,"critique":[{"憑老太太愛在那一處，就在那一處":[{"critic":"庚辰雙行夾批","comment":"必是王夫人如此答方妙。"}]}]
	}
	,{"id":"5"
	,"text":"鳳姐道：「藕香榭已經擺下了，那山坡下兩顆桂花開的又好，河裡的水又碧清，坐在河當中亭子上豈不敞亮，看著水眼也清亮。」"
	,"critique":[{"」":[{"critic":"庚辰雙行夾批","comment":"智者樂水，豈具然乎？"}]}]
	}
	,{"id":"6"
	,"text":"賈母聽了，說：「這話很是。」說著，就引了眾人往藕香榭來。"
	}
	,{"id":"7"
	,"text":"原來這藕香榭蓋在池中，四面有窗，左右有曲廊可通，亦是跨水接岸，後面又有曲折竹橋暗接。"
	}
	,{"id":"8"
	,"text":"眾人上了竹橋，鳳姐忙上來攙著賈母，口裡說：「老祖宗只管邁大步走，不相干的，這竹子橋規矩，咯吱咯喳的。」\n\n"
	,"critique":[{"這竹子橋規矩，咯吱咯喳的":[{"critic":"庚辰雙行夾批","comment":"如見其勢，如臨其上，非走過者形容不到。"}]}]
	}
	,{"id": "9"
	,"text":"\t\t一時進入榭中，只見欄杆外另放著兩張竹案，一個上面設著杯箸酒具，一個上頭設著茶筅、茶盂、各色茶具。那邊有兩三個丫頭煽風爐煮茶，這一邊另外幾個丫頭也煽風爐燙酒呢。"
	,"annotate":[{"茶筅":[{"note":"宋代發明茶筅，又稱「茶刷」，《茶具圖贊》美其名「竺副帥」，形如竹刷，用以攪拌茶湯，使末茶和水均勻混合。" , "illustration":["https://images.pexels.com/photos/8474059/pexels-photo-8474059.jpeg","https://zh.wikipedia.org/wiki/茶筅"] }]}
				,{"茶盂":[{"note":"茶盂用以接收冲茶時多餘或溢出的水，或洗杯、溫杯之用。在古代茶盂、茶碗混名，功能重叠。近代茶盂、茶𥁐（海）又相混名。" , "illustration":["https://tse1.explicit.bing.net/th/id/OIP.aB1gfoxz-Kr_A3CeDEAtMAHaG9","https://tse1.explicit.bing.net/th/id/OIP.U2j00b9IjQWEI6MOhN65_AHaHa"] }]}
				,{"各色茶具":[{"note":"各色茶具。" , "illustration":["https://images.pexels.com/photos/8952013/pexels-photo-8952013.jpeg"] }]}
				,{"風爐煮茶":[{"note":"泥垛的風爐。有通風口可煽風。" , "illustration":["https://media.etmall.com.tw/nximg/00100002403/100002403565/100002403565_xxl.jpg"] }]}]
				
	}
	,{"id": "10"
	,"text":"賈母喜的忙問：「這茶想的到，且是地方，東西都乾淨。」"
	}
	,{"id": "11"
	,"text":"湘雲笑道：「這是寶姐姐幫著我預備的。」"
	}
	,{"id": "12"
	,"text":"賈母道：「我說這個孩子細緻，凡事想的妥當。」一面說，一面又看見柱上掛的黑漆嵌蚌的對子，命人念。湘雲念道：\n\n"
	}
	,{"id": "13"
	,"text":"\t\t\t\t芙蓉影破歸蘭槳，菱藕香深寫竹橋。\n\n"
	,"critique":[{"芙蓉影破歸蘭槳，菱藕香深寫竹橋":[{"critic":"庚辰雙行夾批","comment":"妙極！此處忽又補出一處不入賈政「試才」一回，皆錯綜其事，不作一直筆也。"}]}]
	}
	,{"id": "14"
	,"text":"\t\t賈母聽了，又抬頭看匾，因回頭向薛姨媽道：「我先小時，家裡也有這麼一個亭子，叫做什麼『枕霞閣』。我那時也只像他們這麼大年紀，同姊妹們天天頑去。"
	}
	,{"id": "15"
	,"text":"那日誰知我失了腳掉下去，幾乎沒淹死，好容易救了上來，到底被那木釘把頭碰破了。如今這鬢角上那指頭頂大一塊窩兒就是那殘破了。眾人都怕經了水，又怕冒了風，都說活不得了，誰知竟好了。」"
	}
	,{"id": "16"
	,"text":"鳳姐不等人說，先笑道：「那時要活不得，如今這大福可叫誰享呢！可知老祖宗從小兒的福壽就不小，神差鬼使碰出那個窩兒來，好盛福壽的。壽星老兒頭上原是一個窩兒，因為萬福萬壽盛滿了，所以倒凸高出些來了。」未及說完，賈母與眾人都笑軟了。"
	,"critique":[{"。」":[{"critic":"庚辰雙行夾批","comment":"看他忽用賈母數語，閑閑又補出此書之前似已有一部《十二釵》的一般，令人遙憶不能一見，余則將欲補出 枕霞閣中十二釵來，豈不又添一部新書？"}]}]
	}
	,{"id":"17"
	,"text":"賈母笑道：「這猴兒慣的了不得了，只管拿我取笑起來，恨的我撕你那油嘴。」"
	}
	,{"id": "18"
	,"text":"鳳姐笑道：「回來吃螃蟹，恐積了冷在心裡，討老祖宗笑一笑開開心，一高興多吃兩個就無妨了。」"
	}
	,{"id": "19"
	,"text":"賈母笑道：「明兒叫你日夜跟著我，我倒常笑笑覺的開心，不許回家去。」"
	}
	,{"id": "20"
	,"text":"王夫人笑道：「老太太因為喜歡他，才慣的他這樣，還這樣說，他明兒越發無禮了。」"
	}
	,{"id": "21"
	,"text":"賈母笑道：「我喜歡他這樣，況且他又不是那不知高低的孩子。家常沒人，娘兒們原該這樣。橫豎禮體不錯就罷，沒的倒叫他從神兒似的作什麼。」\n\n"
	,"critique":[{"」":[{"critic":"庚辰雙行夾批","comment":"近之暴發專講理法竟不知禮法，此似無禮而禮法井井，所謂「整瓶不動半瓶搖」，又曰「習慣成自然」，真不謬也。"}]}]
	}
	,{"id": "22"
	,"text":"\t\t說著，一齊進入亭子，獻過茶，鳳姐忙著搭桌子，要杯箸。上面一桌，賈母、薛姨媽、寶釵、黛玉、寶玉；東邊一桌，史湘雲、王夫人、迎、探、惜；西邊靠門一桌，李紈和鳳姐的，虛設坐位，二人皆不敢坐，只在賈母、王夫人兩桌上伺候。"
	}
	,{"id": "23"
	,"text":"鳳姐吩咐：「螃蟹不可多拿來，仍舊放在蒸籠裡，拿十個來，吃了再拿。」"
	}
	,{"id": "24"
	,"text":"一面又要水洗了手，站在賈母跟前剝蟹肉，頭次讓薛姨媽。"
	}
	,{"id": "25"
	,"text":"薛姨媽道：「我自己掰著吃香甜，不用人讓。」"
	}
	,{"id": "26"
	,"text":"鳳姐便奉與賈母。二次的便與寶玉，又說：「把酒燙的滾熱的拿來。」"
	}
	,{"id": "27"
	,"text":"又命小丫頭們去取了菊花葉兒、桂花蕊熏的綠豆麵子來，預備著洗手。"
	,"annotate":[{"綠豆麵子":[{"note":"綠豆粉。粉狀的東西，叫做「麵」子。"}]}]
	}
	,{"id": "28"
	,"text":"史湘雲陪著吃了一個就下座來讓人，又出至外頭，令人盛兩盤子與趙姨娘、周姨娘送去。"
	}
	,{"id": "29"
	,"text":"又見鳳姐走來道：「你不慣張羅，你吃你的去。我先替你張羅，等散了我再吃。」"
	}
	,{"id": "30"
	,"text":"湘雲不肯，又令人在那邊廊上擺了兩桌，讓鴛鴦、琥珀、彩霞、彩雲、平兒去坐。"
	}
	,{"id": "31"
	,"text":"鴛鴦因向鳳姐笑道：「二奶奶在這裡伺候，我們可吃去了。」"
	}
	,{"id": "32"
	,"text":"鳳姐兒道：「你們只管去，都交給我就是了。」說著，史湘雲仍入了席。鳳姐和李紈也胡亂應個景兒。"
	}
	,{"id": "33"
	,"text":"鳳姐仍是下來張羅，一時出至廊上，鴛鴦等正吃的高興，見他來了，鴛鴦等站起來道：「奶奶又出來作什麼？讓我們也受用一會子。」"
	}
	,{"id": "34"
	,"text":"鳳姐笑道：「鴛鴦小蹄子越發壞了，我替你當差，倒不領情，還抱怨我。還不快斟一鐘酒來我喝呢。」"
	}
	,{"id": "35"
	,"text":"鴛鴦笑著忙斟了一杯酒，送至鳳姐唇邊，鳳姐一揚脖子吃了。平兒早剔了一殼黃子送來，鳳姐道：「多倒些薑醋。」"
	}
	,{"id": "36"
	,"text":"一面也吃了，笑道：「你們坐著吃罷，我可去了。」"
	}
	,{"id": "37"
	,"text":"鴛鴦笑道：「好沒臉，吃我們的東西。」"
	}
	,{"id": "38"
	,"text":"鳳姐兒笑道：「你和我少作怪。你知道你璉二爺愛上了你，要和老太太討了你做小老婆呢。」"
	}
	,{"id": "39"
	,"text":"鴛鴦道：「啐，這也是作奶奶說出來的話！我不拿腥手抹你一臉算不得。」"
	}
	,{"id": "40"
	,"text":"說著趕來就要抹。鳳姐兒央道：「好姐姐，饒我這一遭兒罷。」"
	}
	,{"id": "41"
	,"text":"琥珀笑道：「鴛丫頭要去了，平丫頭還饒他？你們看看他，沒有吃了兩個螃蟹，倒喝了一碟子醋，他也算不會攬酸了。」"
	}
	,{"id": "42"
	,"text":"平兒手裡正掰了個滿黃的螃蟹，聽如此奚落他，便拿著螃蟹照著琥珀臉上抹來，口內笑罵：「我把你這嚼舌根的小蹄子！」"
	}
	,{"id": "43"
	,"text":"琥珀也笑著往旁邊一躲，平兒使空了，往前一撞，正恰恰的抹在鳳姐兒腮上。鳳姐兒正和鴛鴦嘲笑，不防唬了一跳，噯喲了一聲。眾人撐不住都哈哈的大笑起來。"
	}
	,{"id": "44"
	,"text":"鳳姐也禁不住笑罵道：「死娼婦！吃離了眼了，混抹你娘的。」"
	}
	,{"id": "45"
	,"text":"平兒忙趕過來替他擦了，親自去端水。鴛鴦道：「阿彌陀佛！這是個報應。」"
	}
	,{"id": "46"
	,"text":"賈母那邊聽見，一疊聲問：「見了什麼這樣樂，告訴我們也笑笑。」"
	}
	,{"id": "47"
	,"text":"鴛鴦等忙高聲笑回道：「二奶奶來搶螃蟹吃，平兒惱了，抹了他主子一臉的螃蟹黃子。主子奴才打架呢。」"
	}
	,{"id": "48"
	,"text":"賈母和王夫人等聽了也笑起來。賈母笑道：「你們看他可憐見的，把那小腿子、臍子給他點子吃也就完了。」"
	}
	,{"id": "49"
	,"text":"鴛鴦等笑著答應了，高聲又說道：「這滿桌子的腿子，二奶奶只管吃就是了。」"
	}
	,{"id": "50"
	,"text":"鳳姐洗了臉走來，又伏侍賈母等吃了一回。"
	}
	,{"id": "51"
	,"text":"黛玉獨不敢多吃，只吃了一點兒夾子肉就下來了。\n\n\n"
	}
	,{"id": "52"
	,"text":"\t\t賈母一時不吃了，大家方散，都洗了手，也有看花的，也有弄水看魚的，遊頑了一回。"
	}
	,{"id": "53"
	,"text":"王夫人因回賈母說：「這裡風大，才又吃了螃蟹，老太太還是回房去歇歇罷了。若高興，明日再來逛逛。」"
	}
	,{"id": "54"
	,"text":"賈母聽了，笑道：「正是呢。我怕你們高興，我走了又怕掃了你們的興。既這麼說，咱們就都去吧。」"
	}
	,{"id": "55"
	,"text":"回頭又囑湘雲：「別讓你寶哥哥、林姐姐多吃了。」湘雲答應著。"
	,"annotate":[{"囑":[{"note":"原刊作「齦」，校作「囑」。"}]}]
	}
	,{"id": "56"
	,"text":"又囑咐湘雲寶釵二人說：「你兩個也別多吃。那東西雖好吃，不是什麼好的，吃多了肚子疼。」"
	}
	,{"id": "57"
	,"text":"二人忙應著送出園外，仍舊回來，令將殘席收拾了另擺。"
	}
	,{"id": "58"
	,"text":"寶玉道：「也不用擺，咱們且作詩。把那大團圓桌就放在當中，酒菜都放著。也不必拘定坐位，有愛吃的大家去吃，散坐豈不便宜。」"
	}
	,{"id": "59"
	,"text":"寶釵道：「這話極是。」"
	}
	,{"id": "60"
	,"text":"湘雲道：「雖如此說，還有別人。」"
	}
	,{"id": "61"
	,"text":"因又命另擺一桌，揀了熱螃蟹來，請襲人、紫鵑、司棋、侍書、入畫、鶯兒、翠墨等一處共坐。山坡桂樹底下鋪下兩條花氈，命答應的婆子並小丫頭等也都坐了，只管隨意吃喝，等使喚再來。\n\n"
	}
	,{"id": "62"
	,"text":"\t\t湘雲便取了詩題，用針綰在牆上。眾人看了，都說：「新奇固新奇，只怕作不出來。」"
	}
	,{"id": "63"
	,"text":"湘雲又把不限韻的原故說了一番。寶玉道：「這才是正理，我也最不喜限韻。」"
	}
	,{"id": "64"
	,"text":"林黛玉因不大吃酒，又不吃螃蟹，自令人掇了一個綉墩，倚欄坐著，拿著釣竿釣魚。寶釵手裡拿著一枝桂花玩了一回，俯在窗檻上掐了桂蕊擲向水面，引的游魚浮上來唼喋。"
	}
	,{"id": "65"
	,"text":"湘雲出一回神，又讓一回襲人等，又招呼山坡下的眾人只管放量吃。探春和李紈、惜春立在垂柳陰中看鷗鷺。迎春又獨在花陰下拿著花針穿茉莉花。 "
	,"critique":[{"。 ":[{"critic":"庚辰雙行夾批","comment":"看他各人各式，亦如畫家有孤聳獨出則有攢三聚五，疏疏密密，直是一幅《百美圖》。"}]}]
	}
	,{"id":"66"
	,"text":"寶玉又看了一回黛玉釣魚，一回又俯在寶釵旁邊說笑兩句，一回又看襲人等吃螃蟹，自己也陪他飲兩口酒。襲人又剝一殼肉給他吃。"
	}
	,{"id":"67"
	,"text":"黛玉放下釣竿，走至座間，拿起那烏銀梅花自斟壺來，揀了一個小小的海棠凍石蕉葉杯。"
	,"critique":[{"拿起那烏銀梅花自斟壺來":[{"critic":"庚辰雙行夾批","comment":"寫壺非寫壺，正寫黛玉。"}]}
				,{"海棠凍石蕉葉杯":[{"critic":"庚辰雙行夾批","comment":"妙杯！非寫杯，正寫黛玉。「揀」字有神理，蓋黛玉不善飲，此任性也。"}]}]
	}
	,{"id":"68"
	,"text":"丫鬟看見，知他要飲酒，忙著走上來斟。黛玉道：「你們只管吃去，讓我自斟，這才有趣兒。」"
	}
	,{"id":"69"
	,"text":"說著便斟了半盞，看時卻是黃酒，因說道：「我吃了一點子螃蟹，覺得心口微微的疼，須得熱熱的喝口燒酒。」"
	}
	,{"id":"70"
	,"text":"寶玉忙道：「有燒酒。」便令將那合歡花浸的酒燙一壺來。黛玉也只吃了一口便放下了。"
	,"critique":[{"合歡花浸的酒燙一壺來":[{"critic":"庚辰雙行夾批","comment":"傷哉！作者猶記矮(畫)舫前以合歡花釀酒乎？屈指二十年矣。"}]}]
	}
	,{"id":"71"
	,"text":"寶釵也走過來，另拿了一隻杯來，也飲了一口，便蘸筆至牆上把頭一個《憶菊》勾了，底下又贅了一個「蘅」字。"
	,"critique":[{"。":[{"critic":"庚辰雙行夾批","comment":"妙極韻極！"}]}]
	}
	,{"id":"72"
	,"text":"寶玉忙道：「好姐姐，第二個我已經有了四句了，你讓我作罷。」"
	}
	,{"id":"73"
	,"text":"寶釵笑道：「我好容易有了一首，你就忙的這樣。」"
	}
	,{"id":"74"
	,"text":"黛玉也不說話，接過筆來把第八個《問菊》勾了，接著把第十一個《菊夢》也勾了，也贅一個「瀟」字。"
	,"critique":[{"。":[{"critic":"庚辰雙行夾批","comment":"這兩個妙題料定黛玉必喜，豈讓人作去哉？"}]}]
	}
	,{"id":"75"
	,"text":"寶玉也拿起筆來，將第二個《訪菊》也勾了，也贅上一個「絳」字。"
	,"critique":[{"「絳」":[{"critic":"飲者","comment":"寶玉默許「絳洞花主」詩號。小時候幹的營生，不是不提它了嗎？"}]}]
	}
	,{"id":"76"
	,"text":"探春走來看看道：「竟沒有人作《簪菊》，讓我作這《簪菊》。」又指著寶玉笑道：「才宣過總不許帶出閨閣字樣來，你可要留神。」"
	}
	,{"id":"77"
	,"text":"說著，只見史湘雲走來，將第四第五《對菊》、《供菊》一連兩個都勾了，也贅上一個「湘」字。"
	}
	,{"id":"78"
	,"text":"探春道：「你也該起個號。」"
	}
	,{"id":"79"
	,"text":"湘雲笑道：「我們家裡如今雖有幾處軒館，我又不住著，借了來也沒趣。」"
	,"critique":[{"我又不住著，借了來也沒趣":[{"critic":"庚辰雙行夾批","comment":"今之不讀書暴發戶偏愛起一別號。一笑。"}]}]
	}
	,{"id":"80"
	,"text":"寶釵笑道：「方纔老太太說，你們家也有這個水亭叫『枕霞閣』，難道不是你的。如今雖沒了，你到底是舊主人。」"
	}
	,{"id":"81"
	,"text":"眾人都道有理，寶玉不待湘雲動手，便代將「湘」字抹了，改了一個「霞」字。"
	}
	,{"id":"82"
	,"text":"又有頓飯工夫，十二題已全，各自謄出來，都交與迎春，另拿了一張雪浪箋過來，一併謄錄出來，某人作的底下贅明某人的號。"
	}
	,{"id":"83"
	,"text":"李紈等從頭看起：\n\n"
	}
	,{"id": "84"
	,"text":"\t\t\t\t《憶菊》\t蘅蕪君\n\n"
	,"critique":[{"蘅蕪君":[{"critic":"庚辰雙行夾批","comment":"真用此號，妙極！"}]}]
	}
	,{"id": "85"
	,"text":"\t\t\t\t悵望西風抱悶思，蓼紅葦白斷腸時。\n"
	,"annotate":[{"蓼紅葦白斷腸時":[{"note":"蓼花紅了，蘆葦白了，秋天斷腸的時節到了。\n蓼花又稱「狗尾巴花」。" , "illustration":["https://www.xian.com/upload/image/202112/13/1bcb8_86c5.jpg","https://tse3.mm.bing.net/th/id/OIP.GZhVG05Z_DFC1M8wZYZwXAHaFj"] }]}]
	}
	,{"id": "86"
	,"text":"\t\t\t\t空籬舊圃秋無跡，瘦月清霜夢有知。\n"
	,"annotate":[{"籬":[{"note":"東晉•陶淵明作有：「採菊東籬下，悠然見南山」，宋•李清照的「東籬把酒黃昏後」。下文凡有「籬」字者，皆從「東籬」典故。"  }]}]
	}
	,{"id": "87"
	,"text":"\t\t\t\t念念心隨歸雁遠，寥寥坐聽晚砧癡。\n"
	,"critique":[{"念念心隨歸雁遠，寥寥坐聽晚砧癡":[{"critic":"飲者","comment":"隱寫寶釵將來成爲棄婦時的心情。"}]}]
	}
	,{"id": "88"
	,"text":"\t\t\t\t誰憐為我黃花病，慰語重陽會有期。\n\n"
	,"critique":[{"慰語重陽會有期":[{"critic":"飲者","comment":"傳統黄菊秋末冬初開花，九九重陽亦在秋末。此回凡寫「重陽秋霜冷」者，皆指花期，引唐•孟浩然《過故人莊》之典故：「故人具雞黍，邀我至田家。綠樹村邊合，青山郭外斜。開軒面場圃，把酒話桑麻。待到重陽日，還來就菊花。」"}]}]
	}
	,{"id": "89"
	,"text":"\t\t\t\t《訪菊》\t怡紅公子\n\n"
	}
	,{"id": "90"
	,"text":"\t\t\t\t閑趁霜晴試一遊，酒盃藥盞莫淹留。\n"
	}
	,{"id": "91"
	,"text":"\t\t\t\t霜前月下誰家種，檻外籬邊何處秋。\n"
	}
	,{"id": "92"
	,"text":"\t\t\t\t蠟屐遠來情得得，冷吟不盡興悠悠。\n"
	}
	,{"id": "93"
	,"text":"\t\t\t\t黃花若解憐詩客，休負今朝掛杖頭。\n\n"
	}
	,{"id": "94"
	,"text":"\t\t\t\t《種菊》\t怡紅公子\n\n"
	}
	,{"id": "95"
	,"text":"\t\t\t\t攜鋤秋圃自移來，籬畔庭前故故栽。\n"
	}
	,{"id": "96"
	,"text":"\t\t\t\t昨夜不期經雨活，今朝猶喜帶霜開。\n"
	}
	,{"id": "97"
	,"text":"\t\t\t\t冷吟秋色詩千首，醉酹寒香酒一杯。\n"
	}
	,{"id": "98"
	,"text":"\t\t\t\t泉溉泥封勤護惜，好知井逕絕塵埃。\n\n"
	}
	,{"id": "99"
	,"text":"\t\t\t\t《對菊》\t枕霞舊友\n\n"
	}
	,{"id": "100"
	,"text":"\t\t\t\t別圃移來貴比金，一叢淺淡一叢深。\n"
	}
	,{"id": "101"
	,"text":"\t\t\t\t蕭疏籬畔科頭坐，清冷香中抱膝吟。\n"
	,"annotate":[{"科頭坐":[{"note":"不戴帽子露髮而坐。 明•沈思孝《九日在告與叔祥小飲》\n\n何處不登台，門扃一徑苔。\n官貧黃菊少，客好綠尊開。\n寒色衣初授，陽春曲並裁。\n科頭松下坐，遮莫朔風來。"}]}
				,{"抱膝吟":[{"note":"《三國志•蜀志•諸葛亮傳》「亮躬耕壟畝，好為《梁父吟》」裴松之註三國魏魚豢《魏略》：「每晨夕從容，常抱膝長嘯。」此以「抱膝吟」指高人志士的吟詠抒懷。"}]}]
	}
	,{"id": "102"
	,"text":"\t\t\t\t數去更無君傲世，看來惟有我知音。\n"
	,"critique":[{"數去更無君傲世，看來惟有我知音":[{"critic":"飲者","comment":"隱寫將來湘雲對黛玉的悼念。"}]}]
	}
	,{"id": "103"
	,"text":"\t\t\t\t秋光荏苒休辜負，相對原宜惜寸陰。\n\n"
	}
	,{"id": "104"
	,"text":"\t\t\t\t《供菊》\t枕霞舊友\n\n"
	}
	,{"id": "105"
	,"text":"\t\t\t\t彈琴酌酒喜堪儔，几案婷婷點綴幽。\n"
	}
	,{"id": "106"
	,"text":"\t\t\t\t隔座香分三徑露，拋書人對一枝秋。\n"
	,"critique":[{"隔座香分三徑露，拋書人對一枝秋":[{"critic":"飲者","comment":"套的是作者自己的「繞堤柳借三篙翠，隔岸花分一脈香」。"}]}]
	}
	,{"id": "107"
	,"text":"\t\t\t\t霜清紙帳來新夢，圃冷斜陽憶舊遊。\n"
	,"annotate":[{"霜清紙帳":[{"note":"花上染的清霜像是裹了層如紙般薄的紗帳。"}]}]
	}
	,{"id": "108"
	,"text":"\t\t\t\t傲世也因同氣味，春風桃李未淹留。\n\n"
	}
	,{"id": "109"
	,"text":"\t\t\t\t《詠菊》\t瀟湘妃子\n\n"
	}
	,{"id": "110"
	,"text":"\t\t\t\t無賴詩魔昏曉侵，繞籬欹石自沉音。\n"
	}
	,{"id": "111"
	,"text":"\t\t\t\t毫端蘊秀臨霜寫，口齒噙香對月吟。\n"
	}
	,{"id": "112"
	,"text":"\t\t\t\t滿紙自憐題素怨，片言誰解訴秋心。\n"
	}
	,{"id": "113"
	,"text":"\t\t\t\t一從陶令平章後，千古高風說到今。\n\n"
	,"annotate":[{"一從陶令平章後":[{"note":"自從陶淵明評說、贊揚菊花後。大家都覺得菊花是花中君子。 東晉•陶淵明：「採菊東籬下，悠然見南山」。宋•周敦頤的《愛蓮說》：「晉陶淵明獨愛菊。」"  }]}]
	}
	,{"id": "114"
	,"text":"\t\t\t\t《畫菊》\t蘅蕪君\n\n"
	}
	,{"id": "115"
	,"text":"\t\t\t\t詩餘戲筆不知狂，豈是丹青費較量。\n"
	}
	,{"id": "116"
	,"text":"\t\t\t\t聚葉潑成千點墨，攢花染出幾霜痕。\n"
	}
	,{"id": "117"
	,"text":"\t\t\t\t淡濃神會風前影，跳脫秋生腕底香。\n"
	}
	,{"id": "118"
	,"text":"\t\t\t\t莫認東籬閑採掇，粘屏聊以慰重陽。\n\n"
	}
	,{"id": "119"
	,"text":"\t\t\t\t《問菊》\t瀟湘妃子\n\n"
	}
	,{"id": "120"
	,"text":"\t\t\t\t欲訊秋情眾莫知，喃喃負手叩東籬。\n"
	}
	,{"id": "121"
	,"text":"\t\t\t\t孤標傲世偕誰隱，一樣花開為底遲？\n"
	,"annotate":[{"為底":[{"note":"為底，即爲何。菊，秋天才開花，故問「爲何遲？」"}]}]
	}
	,{"id": "122"
	,"text":"\t\t\t\t圃露庭霜何寂寞，雁歸蛩病可相思？\n"
	}
	,{"id": "123"
	,"text":"\t\t\t\t休言舉世無談者，解語何妨片語時。\n\n"
	}
	,{"id": "124"
	,"text":"\t\t\t\t《簪菊》\t蕉下客\n\n"
	}
	,{"id": "125"
	,"text":"\t\t\t\t瓶供籬栽日日忙，折來休認鏡中妝。\n"
	}
	,{"id": "126"
	,"text":"\t\t\t\t長安公子因花癖，彭澤先生是酒狂。\n"
	,"annotate":[{"長安公子因花癖":[{"note":"長安公子菊花插滿頭。指唐詩人杜牧，長安人，其《九日齊山登高》詩寫：\n\n塵世難逢開口笑，菊花須插滿頭歸。\n但將酩酊酬佳節，不用登臨嘆落暉。"}]}
				,{"彭澤先生是酒狂":[{"note":"陶淵明曾任彭澤令。除愛菊外，也愛酒。其《五柳先生傳》自言「性嗜酒」。"}]}]
	}
	,{"id": "127"
	,"text":"\t\t\t\t短鬢冷沾三徑露，葛巾香染九秋霜。\n"
	,"critique":[{"短鬢冷沾三徑露，葛巾香染九秋霜":[{"critic":"飲者","comment":"套的還是作者自己的「繞堤柳借三篙翠，隔岸花分一脈香」。"}]}]
	}
	,{"id": "128"
	,"text":"\t\t\t\t高情不入時人眼，拍手憑他笑路旁。\n\n"
	}
	,{"id": "129"
	,"text":"\t\t\t\t《菊影》\t枕霞舊友\n\n"
	}
	,{"id": "130"
	,"text":"\t\t\t\t秋光疊疊復重重，潛度偷移三徑中。\n"
	}
	,{"id": "131"
	,"text":"\t\t\t\t窗隔疏燈描遠近，籬篩破月鎖玲瓏。\n"
	}
	,{"id": "132"
	,"text":"\t\t\t\t寒芳留照魂應駐，霜印傳神夢也空。\n"
	}
	,{"id": "133"
	,"text":"\t\t\t\t珍重暗香休踏碎，憑誰醉眼認朦朧。\n\n"
	}
	,{"id": "134"
	,"text":"\t\t\t\t《菊夢》\t瀟湘妃子\n\n"
	}
	,{"id": "135"
	,"text":"\t\t\t\t籬畔秋酣一覺清，和雲伴月不分明。\n"
	}
	,{"id": "136"
	,"text":"\t\t\t\t登仙非慕莊生蝶，憶舊還尋陶令盟。\n"
	}
	,{"id": "137"
	,"text":"\t\t\t\t睡去依依隨雁斷，驚回故故惱蛩鳴。\n"
	}
	,{"id": "138"
	,"text":"\t\t\t\t醒時幽怨同誰訴，衰草寒煙無限情。\n\n"
	}
	,{"id": "139"
	,"text":"\t\t\t\t《殘菊》\t蕉下客\n\n"
	}
	,{"id": "140"
	,"text":"\t\t\t\t露凝霜重漸傾欹，宴賞才過小雪時。\n"
	}
	,{"id": "141"
	,"text":"\t\t\t\t蒂有餘香金淡泊，枝無全葉翠離披。\n"
	,"annotate":[{"翠離披":[{"note":"「翠離披」， 指菊花的綠葉天生得破碎散亂不齊整的樣子。", "illustration":["https://images.pexels.com/photos/14134485/pexels-photo-14134485.jpeg"]}]}]
	}
	,{"id": "142"
	,"text":"\t\t\t\t半床落月蛩聲病，萬里寒雲雁陣遲。\n"
	}
	,{"id": "143"
	,"text":"\t\t\t\t明歲秋風知再會，暫時分手莫相思。\n\n"
	}
	,{"id": "144"
	,"text":"\t\t眾人看一首，贊一首，彼此稱揚不已。"
	}
	,{"id": "145"
	,"text":"李紈笑道：「等我從公評來。通篇看來，各有各人的警句。今日公評：《詠菊》第一，《問菊》第二，《菊夢》第三，題目新，詩也新，立意更新，惱不得要推瀟湘妃子為魁了；然後《簪菊》《對菊》《供菊》《畫菊》《憶菊》次之。」"
	}
	,{"id": "146"
	,"text":"寶玉聽說，喜的拍手叫「極是，極公道。」"
	}
	,{"id": "147"
	,"text":"黛玉道：「我那首也不好，到底傷於纖巧些。」"
	}
	,{"id": "148"
	,"text":"李紈道：「巧的卻好，不露堆砌生硬。」"
	}
	,{"id": "149"
	,"text":"黛玉道：「據我看來，頭一句好的是『圃冷斜陽憶舊遊』，這句背面傅粉。『拋書人對一枝秋』已經妙絕，將供菊說完，沒處再說，故翻回來想到未折未供之先，意思深透。」"
	}
	,{"id": "150"
	,"text":"李紈笑道：「固如此說，你的『口齒噙香』句也敵的過了。」"
	}
	,{"id": "151"
	,"text":"探春又道：「到底要算蘅蕪君沉著，『秋無跡』、『夢有知』，把個憶字竟烘染出來了。」"
	}
	,{"id": "152"
	,"text":"寶釵笑道：「你的『短鬢冷沾』、『葛巾香染』，也就把簪菊形容的一個縫兒也沒了。」"
	}
	,{"id": "153"
	,"text":"湘雲道：「『偕誰隱』、『為底遲』，真個把個菊花問的無言可對。」"
	}
	,{"id": "154"
	,"text":"李紈笑道：「你的『科頭坐』、『抱膝吟』，竟一時也不能別開，菊花有知，也必膩煩了。」說的大家都笑了。"
	}
	,{"id": "155"
	,"text":"寶玉笑道：「我又落第。難道『誰家種』、『何處秋』、『蠟屐遠來』、『冷吟不盡』，都不是訪，『昨夜雨』、『今朝霜』，都不是種不成？但恨敵不上『口齒噙香對月吟』、『清冷香中抱膝吟』、『短鬢』、『葛巾』、『金淡泊』、『翠離披』、『秋無跡』、『夢有知』這幾句罷了。」"
	,"critique":[{"。」":[{"critic":"庚辰雙行夾批","comment":"總寫寶玉不及，妙極！"}]}]
	}
	,{"id":"156"
	,"text":"又道：「明兒閑了，我一個人作出十二首來。」"
	}
	,{"id":"157"
	,"text":"李紈道：「你的也好，只是不及這幾句新巧就是了。」\n\n\n"
	}
	,{"id": "158"
	,"text":"\t\t大家又評了一回，復又要了熱蟹來，就在大圓桌子上吃了一回。"
	}
	,{"id":"159"
	,"text":"寶玉笑道：「今日持螯賞桂，亦不可無詩。我已吟成，誰還敢作呢？」說著，便忙洗了手提筆寫出。眾人看道：\n\n"
	,"critique":[{"不可無詩":[{"critic":"庚辰雙行夾批","comment":"全是他忙，全是他不及。妙極！"}]}
				,{"提筆寫出":[{"critic":"庚辰雙行夾批","comment":"且莫看詩，只看他偏於如許一大回詩，後又寫一回詩，豈世人想得到的？"}
				,{"critic":"飲者","comment":"寶玉自我側寫「橫行公子」、「一生忙」也。"}]}]
	}
	,{"id": "160"
	,"text":"\t\t\t\t持螯更喜桂陰涼，潑醋擂薑興欲狂。\n"
	}
	,{"id": "161"
	,"text":"\t\t\t\t饕餮王孫應有酒，橫行公子卻無腸。\n"
	}
	,{"id": "162"
	,"text":"\t\t\t\t臍間積冷饞忘忌，指上沾腥洗尚香。\n"
	}
	,{"id": "163"
	,"text":"\t\t\t\t原為世人美口腹，坡仙曾笑一生忙。\n\n"
	,"annotate":[{"坡仙曾笑一生忙":[{"note":"東坡先生曾自嘲笑一生為口忙。有《初到黄州》詩曰：\n\n自笑平生為口忙，老來事業轉荒唐。\n長江繞郭知魚美，好竹連山覺筍香。\n逐客不妨員外置，詩人例作水曹郎。\n只慚無補絲毫事，尚費官家壓酒囊。"}]}]
	}
	,{"id": "164"
	,"text":"\t\t黛玉笑道：「這樣的詩，要一百首也有。」"
	,"critique":[{"」":[{"critic":"庚辰雙行夾批","comment":"看他這一說。"}]}]
	}
	,{"id":"165"
	,"text":"寶玉笑道：「你這會子才力已盡，不說不能作了，還貶人家。」"
	}
	,{"id":"166"
	,"text":"黛玉聽了，並不答言，也不思索，提起筆來一揮，已有了一首。眾人看道：\n\n"
	}
	,{"id": "167"
	,"text":"\t\t\t\t鐵甲長戈死未忘，堆盤色相喜先嘗。\n"
	}
	,{"id": "168"
	,"text":"\t\t\t\t螯封嫩玉雙雙滿，殼凸紅脂塊塊香。\n"
	}
	,{"id": "169"
	,"text":"\t\t\t\t多肉更憐卿八足，助情誰勸我千觴。\n"
	}
	,{"id": "170"
	,"text":"\t\t\t\t對斯佳品酬佳節，桂拂清風菊帶霜。\n\n"
	}
	,{"id": "171"
	,"text":"\t\t寶玉看了正喝彩，黛玉便一把撕了，令人燒去，因笑道：「我的不及你的，我燒了他。你那個很好，比方纔的菊花詩還好，你留著他給人看。」"
	}
	,{"id": "172"
	,"text":"寶釵接著笑道：「我也勉強了一首，未必好，寫出來取笑兒罷。」"
	}
	,{"id": "173"
	,"text":"說著也寫了出來。大家看時，寫道是：\n\n"
	}
	,{"id": "174"
	,"text":"\t\t\t\t桂靄桐陰坐舉觴，長安涎口盼重陽。\n"
	,"annotate":[{"桂靄桐陰":[{"note":"桂花樹與梧桐的樹蔭下。"}]}
				,{"觴":[{"note":"觴（音 傷），酒杯。《詩•周南•卷耳疏》一升曰爵，二升曰觚（孤），三升曰觶（至），四升曰角，五升曰散，總名曰爵，其實曰觴。觴者，餉也。" , "illustration":["https://tse1.mm.bing.net/th/id/OIP.KRgRFdgM-ACnNeHr_zuH9wHaKn","https://www.kurodatoen.co.jp/wp-content/uploads/2023/06/412f52ae497b207f3d0d90181eb129f1.jpg"] }]}]
	}
	,{"id": "175"
	,"text":"\t\t\t\t眼前道路無經緯，皮裡春秋空黑黃。\n\n"
	,"critique":[{"皮裡春秋空黑黃":[{"critic":"飲者","comment":"反襯雨村的「讀書人不在黃道黑道，總以事理為要。」非真讀書人，自是「皮裡春秋空黑黃」，不在乎事理，只追逐勢利。雨村、寶釵終墜此道。"}]}]
	}
	,{"id": "176"
	,"text":"\t\t看到這裡，眾人不禁叫絕。寶玉道：「寫得痛快！我的詩也該燒了。」又看底下道：\n\n"
	}
	,{"id": "177"
	,"text":"\t\t\t\t酒未敵腥還用菊，性防積冷定須薑。\n"
	,"annotate":[{"性防積冷定須薑":[{"note":"蟹肉性冷，常搭配薑絲來中和。"}]}]
	}
	,{"id": "178"
	,"text":"\t\t\t\t於今落釜成何益，月浦空餘禾黍香。\n\n"
	,"annotate":[{"月浦":[{"note":"秋天水邊的月夜。蟹肉肥美的季節在於秋。以「月」暗點中秋。"}]}]
	}
	,{"id": "179"
	,"text":"\t\t眾人看畢，都說這是食螃蟹絕唱，這些小題目，原要寓大意才算是大才，只是諷刺世人太毒了些。\n\n"
	}
	,{"id": "180"
	,"text":"\t\t說著，只見平兒復進園來。不知作什麼，且聽下回分解。\n\n"
	}
	,{"postscript":""
    ,"text":"\t\t【回後批語】\n\n"
    ,"critique":[{"【回後批語】":[{"critic":"蒙回末總批","comment":"請看此回中，閨中女兒能作此等豪情韻事，且筆下各能自畫其性情，毫不乖舛。作者之錦繡口，無庸贅續。其用意之深，獎勵之勤，都此文者亦不得輕忽戒之也。"}]}]
	}
]}
